{
  "adapter_name": "client",
  "analysis_context": "Automated pattern detection",
  "bug_id": "SCAN_R122_client_L491",
  "code_sample": "                anyhow::bail!(\"Logon timeout\".to_string());",
  "description": "Performance detected: literal.to_string()",
  "file_location": {
    "column": 31,
    "line": 491,
    "relative_path": "../crates/adapters/coinbase_intx/src/fix/client.rs"
  },
  "fix_suggestion": "Review performance pattern usage",
  "pattern_id": "R122",
  "severity": "High",
  "timestamp": "20250826_112741",
  "workspace_info": {
    "branch": "develop",
    "repository": "nautilus_trader"
  }
}