{
  "adapter_name": "live",
  "analysis_context": "Automated pattern detection",
  "bug_id": "SCAN_R067_live_L53",
  "code_sample": "#[allow(clippy::large_enum_variant)] // TODO: Optimize this (largest variant 1096 vs 80 bytes)",
  "description": "Style detected: TODO comment",
  "file_location": {
    "column": 41,
    "line": 53,
    "relative_path": "../crates/adapters/databento/src/live.rs"
  },
  "fix_suggestion": "Review style pattern usage",
  "pattern_id": "R067",
  "severity": "High",
  "timestamp": "20250826_112747",
  "workspace_info": {
    "branch": "develop",
    "repository": "nautilus_trader"
  }
}