{
  "adapter_name": "client",
  "analysis_context": "Automated pattern detection",
  "bug_id": "SCAN_R067_client_L401",
  "code_sample": "                // TODO: Implement RPC unsubscription when available",
  "description": "Style detected: TODO comment",
  "file_location": {
    "column": 20,
    "line": 401,
    "relative_path": "../crates/adapters/blockchain/src/data/client.rs"
  },
  "fix_suggestion": "Review style pattern usage",
  "pattern_id": "R067",
  "severity": "High",
  "timestamp": "20250826_112743",
  "workspace_info": {
    "branch": "develop",
    "repository": "nautilus_trader"
  }
}